AUTHORS
ChangeLog
README.rst
setup.cfg
setup.py
etc/wan_qos_agent.ini
etc/wan_qos_plugin.ini
tc_as_a_service.egg-info/PKG-INFO
tc_as_a_service.egg-info/SOURCES.txt
tc_as_a_service.egg-info/dependency_links.txt
tc_as_a_service.egg-info/entry_points.txt
tc_as_a_service.egg-info/not-zip-safe
tc_as_a_service.egg-info/pbr.json
tc_as_a_service.egg-info/top_level.txt
wan_qos/__init__.py
wan_qos/agent/__init__.py
wan_qos/agent/agent_api.py
wan_qos/agent/tc_agent.py
wan_qos/agent/tc_driver.py
wan_qos/agent/tc_manager.py
wan_qos/cmd/__init__.py
wan_qos/cmd/eventlet/__init__.py
wan_qos/cmd/eventlet/agent.py
wan_qos/common/__init__.py
wan_qos/common/api.py
wan_qos/common/constants.py
wan_qos/common/topics.py
wan_qos/db/__init__.py
wan_qos/db/wan_qos_db.py
wan_qos/db/migration/__init__.py
wan_qos/db/migration/alembic_migrations/__init__.py
wan_qos/db/migration/alembic_migrations/env.py
wan_qos/db/migration/alembic_migrations/script.py.mako
wan_qos/db/migration/alembic_migrations/versions/__init__.py
wan_qos/db/migration/alembic_migrations/versions/ocata/__init__.py
wan_qos/db/migration/alembic_migrations/versions/ocata/contract/45194b1d3492_first_rev.py
wan_qos/db/migration/alembic_migrations/versions/ocata/contract/__init__.py
wan_qos/db/models/__init__.py
wan_qos/db/models/wan_tc.py
wan_qos/extensions/__init__.py
wan_qos/extensions/wantc.py
wan_qos/extensions/wantcclass.py
wan_qos/extensions/wantcdevice.py
wan_qos/extensions/wantcfilter.py
wan_qos/services/__init__.py
wan_qos/services/plugin.py
wan_qos/tests/__init__.py
wan_qos/tests/system/__init__.py
wan_qos/tests/system/plugin.py
wan_qos/tests/unit/__init__.py
wan_qos/tests/unit/test_db.py
wan_qos/tests/unit/test_tc_agent.py
wan_qos/wanqos_client/__init__.py
wan_qos/wanqos_client/_wantc.py
wan_qos/wanqos_client/_wantcclass.py
wan_qos/wanqos_client/_wantcdevice.py
wan_qos/wanqos_client/_wantcfilter.py